code_ally/__init__.py
code_ally/_version.py
code_ally/config.py
code_ally/main.py
code_ally/service_registry.py
code_ally/trust.py
code_ally/agent/__init__.py
code_ally/agent/agent.py
code_ally/agent/command_handler.py
code_ally/agent/error_handler.py
code_ally/agent/permission_manager.py
code_ally/agent/task_planner.py
code_ally/agent/token_manager.py
code_ally/agent/tool_manager.py
code_ally/agent/ui_manager.py
code_ally/llm_client/__init__.py
code_ally/llm_client/model_client.py
code_ally/llm_client/ollama_client.py
code_ally/prompts/__init__.py
code_ally/prompts/directory_config.py
code_ally/prompts/directory_utils.py
code_ally/prompts/system_messages.py
code_ally/tools/__init__.py
code_ally/tools/base.py
code_ally/tools/bash.py
code_ally/tools/batch.py
code_ally/tools/code.py
code_ally/tools/directory.py
code_ally/tools/edit.py
code_ally/tools/glob.py
code_ally/tools/grep.py
code_ally/tools/plan.py
code_ally/tools/read.py
code_ally/tools/refactor.py
code_ally/tools/registry.py
code_ally/tools/write.py
code_ally-0.6.0.dist-info/licenses/LICENSE
code_ally-0.6.0.dist-info/METADATA
code_ally-0.6.0.dist-info/WHEEL
code_ally-0.6.0.dist-info/entry_points.txt
code_ally-0.6.0.dist-info/top_level.txt
code_ally-0.6.0.dist-info/RECORD
