Metadata-Version: 2.4
Name: code_ally
Version: 0.6.0
Summary: A local LLM-powered pair programming assistant
Author-email: Ben H Moore <ben@benhmoore.com>
License: MIT
Project-URL: Homepage, https://github.com/benhmoore/CodeAlly
Project-URL: Bug Tracker, https://github.com/benhmoore/CodeAlly/issues
Project-URL: Documentation, https://github.com/benhmoore/CodeAlly/blob/main/README.md
Project-URL: Source Code, https://github.com/benhmoore/CodeAlly
Keywords: llm,ai,pair programming,code assistant,development
Classifier: Development Status :: 3 - Alpha
Classifier: Intended Audience :: Developers
Classifier: Topic :: Software Development
Classifier: Programming Language :: Python :: 3
Classifier: Programming Language :: Python :: 3.10
Classifier: Programming Language :: Python :: 3.11
Classifier: Programming Language :: Python :: 3.12
Classifier: Operating System :: OS Independent
Classifier: License :: OSI Approved :: MIT License
Requires-Python: >=3.10
License-File: LICENSE
Requires-Dist: requests>=2.32.0
Requires-Dist: rich>=13.0.0
Requires-Dist: prompt_toolkit>=3.0.0
Provides-Extra: dev
Requires-Dist: black>=24.3.0; extra == "dev"
Requires-Dist: isort>=5.13.2; extra == "dev"
Requires-Dist: mypy>=1.9.0; extra == "dev"
Requires-Dist: pytest>=8.0.0; extra == "dev"
Requires-Dist: pytest-cov>=5.0.0; extra == "dev"
Requires-Dist: ruff>=0.3.0; extra == "dev"
Requires-Dist: pre-commit>=3.6.0; extra == "dev"
Requires-Dist: build>=1.0.3; extra == "dev"
Requires-Dist: twine>=6.0.0; extra == "dev"
Requires-Dist: hatch>=1.8.0; extra == "dev"
Dynamic: license-file
